palladio/MPIGridSearchCV.py
palladio/MPINestedGridSearchCV.py
palladio/__init__.py
palladio/analysis.py
palladio/colors.py
palladio/datasets.py
palladio/job_distribution.py
palladio/metrics.py
palladio/model_assessment.py
palladio/plotting.py
palladio/preprocessing.py
palladio/session.py
palladio/utils.py
palladio/config_templates/__init__.py
palladio/config_templates/config_binclass.py
palladio/config_templates/default_config.py
palladio/wrappers/__init__.py
palladio/wrappers/_lasso_ols.py
palladio/wrappers/_pipeline.py
palladio/wrappers/_ridge_regression.py
palladio/wrappers/classifier.py
palladio/wrappers/feature_selection.py
palladio-2.0.4rc1.data/scripts/pd_analysis.py
palladio-2.0.4rc1.data/scripts/pd_merge_sessions.py
palladio-2.0.4rc1.data/scripts/pd_run.py
palladio-2.0.4rc1.dist-info/DESCRIPTION.rst
palladio-2.0.4rc1.dist-info/METADATA
palladio-2.0.4rc1.dist-info/RECORD
palladio-2.0.4rc1.dist-info/WHEEL
palladio-2.0.4rc1.dist-info/metadata.json
palladio-2.0.4rc1.dist-info/top_level.txt
