Metadata-Version: 2.0
Name: palladio
Version: 2.0.4rc1
Summary: ParALleL frAmework for moDel selectIOn
Home-page: https://github.com/slipguru/palladio
Author: Matteo Barbieri, Samuele Fiorini, Federico Tomasi
Author-email: {matteo.barbieri, samuele.fiorini, federico.tomasi}@dibris.unige.it
License: FreeBSD
Download-URL: https://github.com/slipguru/palladio/tarball/2.0.4rc1
Platform: UNKNOWN
Classifier: Development Status :: 4 - Beta
Classifier: Environment :: Console
Classifier: Intended Audience :: Science/Research
Classifier: Intended Audience :: Developers
Classifier: Programming Language :: Python
Classifier: License :: OSI Approved :: BSD License
Classifier: Topic :: Software Development
Classifier: Topic :: Scientific/Engineering :: Bio-Informatics
Classifier: Operating System :: POSIX
Classifier: Operating System :: Unix
Classifier: Operating System :: MacOS
Requires-Dist: joblib
Requires-Dist: matplotlib (>=1.5.1)
Requires-Dist: numpy (>=1.10.1)
Requires-Dist: scikit-learn (>=0.18)
Requires-Dist: scipy (>=0.16.1)
Requires-Dist: seaborn (>=0.7.0)
